{
  "config": {
    "probability": 0.25,
    "cutoff_height": 70,
    "tallness": {
      "type": "minecraft:uniform",
      "min_inclusive": { "absolute": 11 },
      "max_inclusive": { "absolute": 30 }
    },
    "lava_level": {
      "above_bottom": 10
    },
    "aquifers_enabled": false,
    "y": {
      "min_inclusive": {
        "absolute": 40
      },
      "max_inclusive": {
        "absolute": 48
      },
      "inner": 1,
      "type": "minecraft:biased_to_bottom"
    },
    "yScale": 0.5,
    "horizontal_radius_multiplier": 1.0,
    "vertical_radius_multiplier": 1.0,
    "floor_level": -0.7
  },
  "type": "ultra_amplified_dimension:ravine"
}